habitat/__init__.py
habitat/py.typed
habitat/version.py
habitat/articulated_agent_controllers/__init__.py
habitat/articulated_agent_controllers/humanoid_base_controller.py
habitat/articulated_agent_controllers/humanoid_rearrange_controller.py
habitat/articulated_agent_controllers/humanoid_seq_pose_controller.py
habitat/articulated_agents/__init__.py
habitat/articulated_agents/articulated_agent_base.py
habitat/articulated_agents/articulated_agent_interface.py
habitat/articulated_agents/manipulator.py
habitat/articulated_agents/mobile_manipulator.py
habitat/articulated_agents/static_manipulator.py
habitat/articulated_agents/humanoids/__init__.py
habitat/articulated_agents/humanoids/kinematic_humanoid.py
habitat/articulated_agents/robots/__init__.py
habitat/articulated_agents/robots/fetch_robot.py
habitat/articulated_agents/robots/fetch_suction.py
habitat/articulated_agents/robots/franka_robot.py
habitat/articulated_agents/robots/spot_robot.py
habitat/articulated_agents/robots/stretch_robot.py
habitat/config/CONFIG_KEYS.md
habitat/config/README.md
habitat/config/__init__.py
habitat/config/default.py
habitat/config/default_structured_configs.py
habitat/config/read_write.py
habitat/config/benchmark/multi_agent/hssd_spot_human.yaml
habitat/config/benchmark/multi_agent/hssd_spot_human_social_nav.yaml
habitat/config/benchmark/multi_agent/pddl/multi_agent_social_nav.yaml
habitat/config/benchmark/multi_agent/pddl/multi_agent_tidy_house.yaml
habitat/config/benchmark/nav/eqa_mp3d.yaml
habitat/config/benchmark/nav/eqa_rgbonly_mp3d.yaml
habitat/config/benchmark/nav/vln_r2r.yaml
habitat/config/benchmark/nav/imagenav/imagenav_base.yaml
habitat/config/benchmark/nav/imagenav/imagenav_gibson.yaml
habitat/config/benchmark/nav/imagenav/imagenav_mp3d.yaml
habitat/config/benchmark/nav/imagenav/imagenav_test.yaml
habitat/config/benchmark/nav/instance_imagenav/instance_imagenav_hm3d_v1.yaml
habitat/config/benchmark/nav/instance_imagenav/instance_imagenav_hm3d_v2.yaml
habitat_lab-0.3.220241205.dist-info/METADATA
habitat_lab-0.3.220241205.dist-info/WHEEL
habitat_lab-0.3.220241205.dist-info/top_level.txt
habitat_lab-0.3.220241205.dist-info/RECORD
